geodataset/__init__.py
geodataset/custom_geodataset.py
geodataset/geodataset.py
geodataset/interpolation.py
geodataset/tools.py
geodataset/utils.py
geodataset/examples/__init__.py
geodataset/examples/selector.py
geodataset/tests/__init__.py
geodataset/tests/base_for_tests.py
geodataset/tests/test_custom_geodataset.py
geodataset/tests/test_geodataset.py
geodataset/tests/test_tools.py
geodataset/tests/test_utils.py
geodataset-0.3.2.dist-info/licenses/LICENSE
geodataset-0.3.2.dist-info/METADATA
geodataset-0.3.2.dist-info/WHEEL
geodataset-0.3.2.dist-info/top_level.txt
geodataset-0.3.2.dist-info/RECORD
